application/__init__.py
application/config/__init__.py
application/config/config.py
application/extensions/__init__.py
application/extensions/init_apscheduler.py
application/extensions/init_cli.py
application/extensions/init_dotenv.py
application/extensions/init_sqlalchemy.py
application/models/__init__.py
application/views/__init__.py
application/views/api1.py
flask_wheel-0.0.4.dist-info/METADATA
flask_wheel-0.0.4.dist-info/WHEEL
flask_wheel-0.0.4.dist-info/top_level.txt
flask_wheel-0.0.4.dist-info/RECORD
