Metadata-Version: 2.1
Name: flask-wheel
Version: 0.0.4
Summary: basic flask project
License: UNKNOWN
Platform: UNKNOWN
